README.md
setup.cfg
setup.py
pbsonesignal/__init__.py
pbsonesignal/exceptions.py
pybossa_onesignal.egg-info/PKG-INFO
pybossa_onesignal.egg-info/SOURCES.txt
pybossa_onesignal.egg-info/dependency_links.txt
pybossa_onesignal.egg-info/requires.txt
pybossa_onesignal.egg-info/top_level.txt