Metadata-Version: 1.1
Name: pybossa-onesignal
Version: 1.1
Summary: pybossa-onesignal is a small library to send Web PUSH notifications within PYBOSSA ecosystem.
Home-page: https://github.com/Scifabric/pybossa-onesignal
Author: Scifabric LTD
Author-email: info@scifabric.com
License: AGPLv3
Download-URL: https://github.com/Scifabric/pybossa-onesignal/zipball/master
Platform: UNKNOWN
Classifier: Development Status :: 3 - Alpha
Classifier: Environment :: Console
Classifier: Intended Audience :: Developers
Classifier: License :: OSI Approved :: GNU Affero General Public License v3 or later (AGPLv3+)
Classifier: Operating System :: OS Independent
Classifier: Programming Language :: Python
Classifier: Topic :: Software Development :: Libraries :: Python Modules
